asyncio_red/__init__.py
asyncio_red/__main__.py
asyncio_red/cmd/__init__.py
asyncio_red/cmd/init.py
asyncio_red/cmd/pull.py
asyncio_red/cmd/push.py
asyncio_red/consumer/__init__.py
asyncio_red/consumer/base.py
asyncio_red/consumer/channels.py
asyncio_red/consumer/lists.py
asyncio_red/consumer/streams/__init__.py
asyncio_red/consumer/streams/streams.py
asyncio_red/consumer/streams/xtrim.lua
asyncio_red/errors.py
asyncio_red/events.py
asyncio_red/red.py
asyncio_red-0.3.7.dist-info/METADATA
asyncio_red-0.3.7.dist-info/WHEEL
asyncio_red-0.3.7.dist-info/entry_points.txt
asyncio_red-0.3.7.dist-info/RECORD
