Metadata-Version: 2.1
Name: asyncio-red
Version: 0.3.7
Summary: asyncio-red
License: MIT
Author: Dmytro Smyk
Author-email: porovozls@gmail.com
Requires-Python: >=3.12,<4.0
Classifier: License :: OSI Approved :: MIT License
Classifier: Programming Language :: Python :: 3
Classifier: Programming Language :: Python :: 3.12
Classifier: Programming Language :: Python :: 3.13
Requires-Dist: backoff (<3)
Requires-Dist: pydantic (<3)
Requires-Dist: redis (<6)
